LICENSE
MANIFEST.in
README.md
setup.py
celery_s3/__init__.py
celery_s3/tests.py
celery_s3.egg-info/PKG-INFO
celery_s3.egg-info/SOURCES.txt
celery_s3.egg-info/dependency_links.txt
celery_s3.egg-info/requires.txt
celery_s3.egg-info/top_level.txt
celery_s3/backends/__init__.py
celery_s3/backends/s3.py