Metadata-Version: 1.1
Name: celery-s3
Version: 1.0.0
Summary: An S3 result store backend for Celery
Home-page: https://github.com/robgolding63/celery-s3
Author: Rob Golding
Author-email: rob@robgolding.com
License: BSD
Download-URL: https://github.com/robgolding63/celery-s3/downloads
Platform: UNKNOWN
Classifier: Development Status :: 3 - Alpha
Classifier: Programming Language :: Python
Classifier: Programming Language :: Python :: 2
Classifier: Programming Language :: Python :: 2.7
Classifier: Programming Language :: Python :: 3
Classifier: Programming Language :: Python :: 3.6
Classifier: License :: OSI Approved :: BSD License
Classifier: Topic :: Software Development :: Libraries :: Python Modules
Classifier: Topic :: System :: Distributed Computing
Classifier: Programming Language :: Python
Classifier: Operating System :: OS Independent
